dioxide-1.2.0.dist-info/METADATA
dioxide-1.2.0.dist-info/WHEEL
dioxide-1.2.0.dist-info/licenses/LICENSE
dioxide/__init__.py
dioxide/_dioxide_core.abi3.so
dioxide/_dioxide_core.pyi
dioxide/container.py
dioxide/decorators.py
dioxide/py.typed
dioxide/scope.py
dioxide-1.2.0.dist-info/RECORD
