Metadata-Version: 2.4
Name: dioxide
Version: 1.2.0
Classifier: Development Status :: 3 - Alpha
Classifier: Intended Audience :: Developers
Classifier: License :: OSI Approved :: MIT License
Classifier: Programming Language :: Python :: 3
Classifier: Programming Language :: Python :: 3.11
Classifier: Programming Language :: Python :: 3.12
Classifier: Programming Language :: Python :: 3.13
Classifier: Programming Language :: Rust
Classifier: Topic :: Software Development :: Libraries :: Python Modules
Classifier: Typing :: Typed
Requires-Dist: maturin>=1.0,<2.0 ; extra == 'dev'
Requires-Dist: pytest>=8.0 ; extra == 'dev'
Requires-Dist: pytest-cov>=4.1 ; extra == 'dev'
Requires-Dist: behave>=1.2.6 ; extra == 'dev'
Requires-Dist: mypy>=1.8 ; extra == 'dev'
Requires-Dist: ruff>=0.1 ; extra == 'dev'
Requires-Dist: isort>=5.13 ; extra == 'dev'
Requires-Dist: tox>=4.0 ; extra == 'dev'
Requires-Dist: pre-commit>=3.0 ; extra == 'dev'
Requires-Dist: mutmut>=2.4 ; extra == 'dev'
Provides-Extra: dev
License-File: LICENSE
Summary: Fast, Rust-backed declarative dependency injection for Python
Keywords: dependency-injection,di,ioc,rust,container
Author-email: Mike Lane <mikelane@gmail.com>
License: MIT
Requires-Python: >=3.11
Project-URL: Homepage, https://github.com/mikelane/dioxide
Project-URL: Repository, https://github.com/mikelane/dioxide
Project-URL: Issues, https://github.com/mikelane/dioxide/issues
